Whoosh274ZhongwenWendang/README.md
Whoosh274ZhongwenWendang/__init__.py
Whoosh274ZhongwenWendang/__main__.py
Whoosh274ZhongwenWendang/file.epub
Whoosh274ZhongwenWendang/index.html
Whoosh274ZhongwenWendang/css/__init__.py
Whoosh274ZhongwenWendang/css/annotations.css
Whoosh274ZhongwenWendang/css/main.css
Whoosh274ZhongwenWendang/css/normalize.css
Whoosh274ZhongwenWendang/css/popup.css
Whoosh274ZhongwenWendang/font/__init__.py
Whoosh274ZhongwenWendang/font/fontello.eot
Whoosh274ZhongwenWendang/font/fontello.svg
Whoosh274ZhongwenWendang/font/fontello.ttf
Whoosh274ZhongwenWendang/font/fontello.woff
Whoosh274ZhongwenWendang/img/__init__.py
Whoosh274ZhongwenWendang/img/annotator-glyph-sprite.png
Whoosh274ZhongwenWendang/img/annotator-icon-sprite.png
Whoosh274ZhongwenWendang/img/apple-touch-icon.png
Whoosh274ZhongwenWendang/img/cancelfullscreen.png
Whoosh274ZhongwenWendang/img/close.png
Whoosh274ZhongwenWendang/img/fullscreen.png
Whoosh274ZhongwenWendang/img/loader.gif
Whoosh274ZhongwenWendang/img/menu-icon.png
Whoosh274ZhongwenWendang/img/save.png
Whoosh274ZhongwenWendang/img/saved.png
Whoosh274ZhongwenWendang/img/settings-s.png
Whoosh274ZhongwenWendang/img/settings.png
Whoosh274ZhongwenWendang/img/star.png
Whoosh274ZhongwenWendang/js/__init__.py
Whoosh274ZhongwenWendang/js/epub.js
Whoosh274ZhongwenWendang/js/epub.min.js
Whoosh274ZhongwenWendang/js/epub.min.map
Whoosh274ZhongwenWendang/js/hooks.min.js
Whoosh274ZhongwenWendang/js/hooks.min.map
Whoosh274ZhongwenWendang/js/reader.js
Whoosh274ZhongwenWendang/js/reader.js.map
Whoosh274ZhongwenWendang/js/reader.min.js
Whoosh274ZhongwenWendang/js/reader.min.map
Whoosh274ZhongwenWendang/js/hooks/__init__.py
Whoosh274ZhongwenWendang/js/hooks/extensions/__init__.py
Whoosh274ZhongwenWendang/js/hooks/extensions/highlight.js
Whoosh274ZhongwenWendang/js/libs/__init__.py
Whoosh274ZhongwenWendang/js/libs/jquery.min.js
Whoosh274ZhongwenWendang/js/libs/localforage.min.js
Whoosh274ZhongwenWendang/js/libs/screenfull.js
whoosh_2_7_4_zhongwen_wendang-2024.3.5.0.dist-info/METADATA
whoosh_2_7_4_zhongwen_wendang-2024.3.5.0.dist-info/WHEEL
whoosh_2_7_4_zhongwen_wendang-2024.3.5.0.dist-info/entry_points.txt
whoosh_2_7_4_zhongwen_wendang-2024.3.5.0.dist-info/top_level.txt
whoosh_2_7_4_zhongwen_wendang-2024.3.5.0.dist-info/RECORD
